msc/__init__.py
msc/screencap.py
msc_base-0.0.1.dist-info/METADATA
msc_base-0.0.1.dist-info/WHEEL
msc_base-0.0.1.dist-info/top_level.txt
msc_base-0.0.1.dist-info/RECORD
