Metadata-Version: 2.1
Name: msc-base
Version: 0.0.1
Summary: 截图工具-base
Author: KateTseng
Author-email: Kate.TsengK@outlook.com
License: MIT
Keywords: Auto Script Testing
Requires-Python: >=3
